mrextractor/Extractor.py
mrextractor/__init__.py
mrextractor/extractor.py
mrextractor/version.py
mrextractor/features/__init__.py
mrextractor/features/base.py
mrextractor/features/elf.py
mrextractor/features/pe.py
mrextractor/features/utils.py
mrextractor-0.0.1.dev3.dist-info/LICENSE
mrextractor-0.0.1.dev3.dist-info/METADATA
mrextractor-0.0.1.dev3.dist-info/WHEEL
mrextractor-0.0.1.dev3.dist-info/top_level.txt
mrextractor-0.0.1.dev3.dist-info/RECORD
